lightning_extensions/__init__.py
lightning_extensions/base_module.py
lightning_extensions/data_module.py
lightning_extensions/extended_trainer.py
lightning_extensions-0.0.21.dist-info/LICENSE
lightning_extensions-0.0.21.dist-info/METADATA
lightning_extensions-0.0.21.dist-info/WHEEL
lightning_extensions-0.0.21.dist-info/top_level.txt
lightning_extensions-0.0.21.dist-info/RECORD
