Metadata-Version: 2.1
Name: lightning_extensions
Version: 0.0.21
Summary: A small lightning extension package
Author-email: Edvards Zakovskis <edvards1999@gmail.com>
Project-URL: Homepage, https://github.com/EdvardsZ/LightningExtensions
Project-URL: Bug Tracker, https://github.com/EdvardsZ/LightningExtensions/sampleproject/issues
Classifier: Programming Language :: Python :: 3
Classifier: License :: OSI Approved :: MIT License
Classifier: Operating System :: OS Independent
Requires-Python: >=3.8
License-File: LICENSE
